{"id": 4181, "url": "http://proxy-pubminefi.diffusion.finances.gouv.fr/pub/document/18/18395.pdf", "author": "Carole Delga", "title": "INVITATION PRESSE - Carole DELGA se déplacera à Nancy (54) à l'occasion du Congrès annuel de l'UMIH le 5 décembre 2014", "text": " \n \n \nCAROLE DELGA \n \nSECRETAIRE D’ETAT CHARGEE DU COMMERCE, DE L’ARTISANAT, DE LA CONSOMMATION ET DE L’ECONOMIE  \nSOCIALE ET SOLIDAIRE, AUPRES DU MINISTRE DE L’ECONOMIE, DE L’INDUSTRIE ET DU NUMERIQUE \n \nI n v i t a t i o n  p re s s e  \nI n v i t a t i o n  p re s s e  \nwww.economie.gouv.fr \n@CaroleDelga \nParis, le 4 décembre 2014 \nN° 239 \n \nCarole DELGA se déplacera à Nancy (54)  \n \nà l’occasion du Congrès annuel de l’Union des Métiers et de l’Industrie \nde l’Hôtellerie \n \n- Vendredi 5 décembre 2014 - \n \n \nCarole DELGA, Secrétaire d’Etat chargée du Commerce, de l’Artisanat, de la Consommation et de \nl’Economie sociale et solidaire se déplacera à Nancy à l’occasion du Congrès annuel de l’Union \ndes Métiers et de l’Industrie de l’Hôtellerie (UMIH), le vendredi 5 décembre.  \n \nElle visitera également le Centre européen de Recherches et de Formation des Arts Verriers \n(CERFAV) pour échanger avec les professionnels des métiers d’art, qui seront désormais \nreconnus dans le cadre des textes d’application de la loi Artisanat-commerce-Très petites \nentreprises début 2015. \n \nDéroulé \n \n12h00 \nDiscours de clôture du 62ème congrès annuel de l’Union des Métiers et de l’Industrie \nde l’Hôtellerie (UMIH) \nCentre Prouvé, Nancy \n \n13h00 \nDéjeuner avec des acteurs locaux du commerce et de l’artisanat  \nCERFAV, Vannes-le-Châtel  \n[non ouvert à la presse] \n \n14h15 \nVisite du Centre européen de Recherches et de Formation aux Arts Verriers \n(CERFAV) \nVannes-le-Châtel \n \n \nAccréditation auprès de la préfecture de Meurthe-et-Moselle \n03 83 34 26 09  ou roxane.thomas@meurthe-et-moselle.gouv.fr \n \nContacts presse cabinet de Carole DELGA : Sophie DULIBEAU et Anthony PORCHERON \n01 53 18 44 13 - sec.secacess-presse@cabinets.finances.gouv.fr \n", "published_date": "2014-12-04", "section": "Communiques"}