{"id": 4364, "url": "http://proxy-pubminefi.diffusion.finances.gouv.fr/pub/document/18/18026.pdf", "author": "Christian Eckert", "title": "INVITATION PRESSE - Marisol TOURAINE, Christian ECKERT et Laurence ROSSIGNOL : conférence de presse PLFSS 2015le 29 septembre 2014 à 17h30", "text": " \n \n \nMARISOL TOURAINE \nMINISTRE DES AFFAIRES SOCIALES, DE LA SANTE  \nET DES DROITS DES FEMMES \n \nCHRISTIAN ECKERT \nSECRETAIRE D’ETAT CHARGE DU BUDGET \n \nI n v i t a t i o n  p r e s s e  \nI n v i t a t i o n  p r e s s e  \nwww.social-sante.gouv.fr                                                                                           www.economie.gouv.fr \nwww.sante.gouv.fr \n \nParis, le 26 septembre 2014 \nN°035 \n \nMarisol TOURAINE, \nMinistre des Affaires sociales, de la Santé et des Droits des femmes, \n \nChristian ECKERT,  \nSecrétaire d’Etat chargé du Budget  \n \net \n \nLaurence ROSSIGNOL,  \nSecrétaire d’Etat chargée de la Famille, des Personnes âgées et de l’Autonomie \n \n \ntiendront à l’issue de la réunion de la Commission des comptes de la Sécurité sociale,  \n \nune conférence de presse de présentation  \ndu projet de loi de financement de la Sécurité sociale 2015,  \n \nLundi 29 septembre 2014 à 17h30 \n \nMinistère des Finances et des Comptes publics \nCentre de conférence Pierre Mendès France \n139, rue de Bercy \n75012 Paris \n  \n \nAccréditations des journalistes auprès du bureau de presse de Bercy \n01 53 18 33 80 \n \n \n \nContacts presse :  \nCabinet de Marisol TOURAINE   \n01 40 56 60 65  \ncab-ass-presse@sante.gouv.fr \nCabinet de Christian ECKERT    \n01 53 18 45 04  \nsec.sebud-presse@cabinets.finances.gouv.fr  \n", "published_date": "2014-09-26", "section": "Communiques"}