{"id": 4440, "url": "http://proxy-pubminefi.diffusion.finances.gouv.fr/pub/document/18/17868.pdf", "author": null, "title": "Le Gouvernement maintient sa prévision d'impôts sur le revenu", "text": " \n \n \n \n \nMICHEL SAPIN \nMINISTRE DES FINANCES ET DES COMPTES PUBLICS \n \nCHRISTIAN ECKERT \nSECRETAIRE D'ETAT AU BUDGET \n \n \nC o m m u n i q u é  d e  p re s s e  \nC o m m u n i q u é  d e  p re s s e  \n \nwww.economie.gouv.fr \n \nParis, le 20 août 2014 \nN°150 \n \n \n \nLe Gouvernement maintient sa prévision d'impôts sur le revenu \n \n \n \n \n \nSelon certaines informations de presse, le produit de l’impôt sur le revenu 2014 (sur les \nrevenus 2013) serait inférieur de 10 Mds d’€ par rapport au montant attendu. Cette \ninformation est erronée. Le Gouvernement maintient sa prévision d’impôts sur le revenu \nde 71 milliards d’euros cette année.  \n \nL’impôt sur le revenu est établi par fractions successives, en six \"émissions\". A ce jour, \nseules les deux premières émissions sont achevées, ce qui représente une grande \nmajorité des contribuables mais pas la totalité.  \n \nLa prétendue perte de recette procède d’un rapprochement de données non \ncomparables : un produit partiel au titre de ces deux premières émissions d’une part, et le \nproduit total de l’impôt sur le revenu 2014, dont la loi de finances rectificative adoptée cet \nété prévoit qu’il doit atteindre un montant net de 71,2 Mds d’€ d’autre part. Cette \nestimation a déjà intégré l’ensemble des informations disponibles.  \n \n \n \n \n \n \n \nContacts presse \n \nCabinet de Michel SAPIN \n01 53 18 41 13  \nsec.mfcp-presse@cabinets.finances.gouv.fr \n \nCabinet de Christian ECKERT 01 53 18 45 04  \nsec.sebud-presse@cabinets.finances.gouv.fr \n \n", "published_date": "2014-08-20", "section": "Communiques"}