{"id": 2232, "url": "http://proxy-pubminefi.diffusion.finances.gouv.fr/pub/document/18/22492.pdf", "author": null, "title": "Situation mensuelle budgétaire au 30 avril 2017", "text": " \n \n \n \nGERALD DARMANIN \nMINISTRE DE L’ACTION ET DES COMPTES PUBLICS \n \nC o m m u n i q u é  d e  p r e s s e  \nC o m m u n i q u é  d e  p r e s s e  \nwww.economie.gouv.fr \nParis, le 9 juin 2017 \nN°020 \n \n \nSITUATION MENSUELLE BUDGÉTAIRE AU 30 AVRIL 2017 \n \nSolde \n \nLe solde général d’exécution au 30 avril 2017 s’établit à -57,9 Md€ contre -56,5 Md€ à \nfin avril 2016. Le solde à fin avril n’est pas représentatif des perspectives d’exécution qui \nseront éclairées par l’audit des finances publiques conduit par la Cour des comptes à la \ndemande du Premier ministre. \n \n \n \nDépenses \nLes dépenses (budget général et prélèvements sur recettes) atteignent 134,5 Md€ contre \n131,3 Md€ au 30 avril 2016.  \n \nRecettes  \nAu 30 avril 2017, les recettes du budget général (nettes des remboursements et \ndégrèvements) s’établissent à 100,3 Md€ contre 98,5 Md€ à fin avril 2016. \n \n \nLes recettes fiscales nettes sont en augmentation de 2,9 Md€ par rapport au 30 avril 2016. \nLes recettes de TVA sont notamment en hausse de 3,0 Md€.  \nÀ fin avril 2017, les recettes non fiscales sont en diminution de 1,5 Md€ par rapport au \n30 avril 2016. Cette baisse résulte d’une diminution du produit des amendes prononcées par \nl’Autorité de la concurrence et de la non-reconduction de la recette constatée en janvier 2016 \nau titre des redevances d’usage des fréquences radioélectriques.  \nComptes spéciaux  \nLe solde des comptes spéciaux s’établit à -23,7 Md€ à fin avril 2017 contre -23,6 Md€ à \nfin avril 2016. Le solde des comptes spéciaux n’est pas significatif à ce stade de l’année. \n \n \n \nContact presse : Cabinet de Gérald DARMANIN : 01 53 18 45 03 presse.macp@cabinets.finances.gouv.fr \n \n\n- 1 – \n \nLa situation du budget de l’État \n \nAu 30 avril 2017 \n \nAdresses Internet : http://www.economie.gouv.fr/situation-mensuelle-budgetaire-au-30-avril-2017 \nOu : http://www.performance-publique.budget.gouv.fr/ressources-documentaires/documentation-budgetaire/la-situation-mensuelle-du-budget-de-letat.html \n \nSolde \nLe solde général d’exécution au 30 avril 2017 s’établit à –57,9 Md€ contre -56,5 Md€ à fin avril 2016.  \nDépenses \nLes dépenses (budget général et prélèvements sur recettes) atteignent 134,5 Md€ contre 131,3 Md€ au 30 \navril 2016. \nRecettes \nAu 30 avril 2017, les recettes du budget général (nettes des remboursements et dégrèvements) s’établissent à \n100,3 Md€ contre 98,5 Md€ à fin avril 2016. \n \nSolde (hors FMI) \n \nen millions d’euros \n2015 \n2016 \nNiveaux à la fin avril \navril 17 / \navril 16 \n2015 \n2016 \n2017 \nSolde du budget général \n-72 149 \n-75 851 \n-41 650 \n-32 816 \n-34 259 \n  \nDépenses (budget général et prélèvements sur recettes) \n371 805 \n379 818 \n134 978 \n131 325 \n134 511 \n2,4% \nRecettes (nettes des remboursements et dégrèvements) \n299 656 \n303 967 \n93 328 \n98 509 \n100 253 \n1,8% \nSolde des comptes spéciaux \n1 624 \n6 795 \n-18 185 \n-23 644 \n-23 666 \n  \ndont avances aux collectivités territoriales \n74 \n1 381 \n-19 345 \n-20 178 \n-20 440 \n  \nSolde général d’exécution (hors budgets annexes) \n-70 524 \n-69 056 \n-59 836 \n-56 460 \n-57 925 \n  \n \n \nSolde d’exécution (en milliards d’euros) \nvaleurs mensuelles \ncumul depuis le début de l’année \n \n-40\n-35\n-30\n-25\n-20\n-15\n-10\n-5\n0\n5\n10\n15\n20\n25\n30\nJanv.\nFév.\nMars\nAvr.\nMai\nJuin\nJuil.\nAoût\nSept.\nOct.\nNov.\nDéc.\n2016\n2017\n \n-110\n-100\n-90\n-80\n-70\n-60\n-50\n-40\n-30\n-20\n-10\n0\nJanv.\nFév.\nMars\nAvr.\nMai\nJuin\nJuil.\nAoût\nSept.\nOct.\nNov.\nDéc.\n2017\n2016\n \n \n \n\n- 2 – \n \nRecettes (nettes des remboursements & dégrèvements) \n \n \n \n \nen millions d’euros \nExécution \nLFI  \nNiveaux à la fin avril \nVariations à la fin avril \n2016 \n2017 \n2016 \n2017 \nPérimètre \ncourant \nPérimètre \nconstant \nRecettes fiscales - nettes (1) \n284 097 \n292 348 \n94 516 \n97 367 \n3,0% \n2,4% \nImpôt sur le revenu – net (2) \n71 751 \n73 352 \n27 758 \n27 182 \n-2,1% \n-2,1% \nImpôt sur les sociétés – net (1) (3) \n29 990 \n29 127 \n6 832 \n6 429 \n-5,9% \n-5,9% \nTaxe intérieure de consommation sur les produits énergétiques (TICPE) \n15 878 \n10 584 \n4 843 \n3 108 \n-35,8% \n-35,7% \nTaxe sur la valeur ajoutée (TVA) – nette (1) \n144 439 \n149 266 \n48 060 \n51 072 \n6,3% \n6,2% \nAutres recettes fiscales – nettes (1) \n22 039 \n30 019 \n7 022 \n9 576 \n36,4% \n26,8% \nRecettes non fiscales \n16 238 \n14 505 \n3 438 \n1 935 \n-43,7% \n-43,7% \nRecettes du budget général (hors fonds de concours) \n300 335 \n306 853 \n97 953 \n99 302 \n1,4% \n0,8% \nFonds de concours \n3 632 \n3 930 \n556 \n951 \n71,2% \n71,2% \nRecettes du budget général (yc fonds de concours) \n303 967 \n310 783 \n98 509 \n100 253 \n1,8% \n1,2% \n(1) Recettes nettes des remboursements et des dégrèvements ; (2) Recettes d’impôt sur le revenu nettes des remboursements et des dégrèvements ; (3) Hors CSB \n \n \n Recettes fiscales nettes (en milliards d’euros) \n valeurs mensuelles \nécart 2017-2016 (cumul depuis le début de l’année) \n0\n5\n10\n15\n20\n25\n30\n35\nJanv.\nFév.\nMars\nAvr.\nMai\nJuin\nJuil.\nAoût\nSept.\nOct.\nNov.\nDéc.\n2016\n2017\n \n \n-12\n-10\n-8\n-6\n-4\n-2\n0\n2\n4\n6\n8\n10\n12\n14\n16\nJanv.\nFév.\nMars\nAvr.\nMai\nJuin\nJuil.\nAoût\nSept.\nOct.\nNov.\nDéc.\nEcart 2017-2016 à périmètre constant\n \n \nRecettes non fiscales (en milliards d’euros) \nvaleurs mensuelles \nécart 2017-2016 (cumul depuis le début de l’année) \n0\n1\n2\n3\n4\n5\nJanv.\nFév.\nMars\nAvr.\nMai\nJuin\nJuil.\nAoût\nSept.\nOct.\nNov.\nDéc.\n2016\n2017\n \n-3\n-2\n-1\n0\n1\n2\n3\nJanv.\nFév.\nMars\nAvr.\nMai\nJuin\nJuil.\nAoût\nSept.\nOct.\nNov.\nDéc.\nEcart 2017-2016 à périmètre constant\n \n \n \nAvertissement : les pourcentages d’évolution ne sont pas significatifs lorsque le nombre figurant au dénominateur est petit et, de ce fait, ne sont pas affichés (mention « n.s. »). \n\n- 3 – \n \nDépenses (hors remboursements & dégrèvements) \nen millions d’euros \nExécution \nNiveaux à la fin avril \nVariations à la fin avril \n2016 \n2016 \n2017 \nPérimètre \ncourant \nPérimètre \nconstant \nDotation des pouvoirs publics  \n988 \n988 \n991 \n0,3% \n0,3% \nDépenses de personnel \n123 191 \n41 647 \n42 977 \n3,2% \n3,2% \nDépenses de fonctionnement  \n52 760 \n19 253 \n20 583 \n6,9% \n6,1% \nCharges de la dette de l’État  \n41 447 \n16 856 \n15 489 \n-8,1% \n-8,1% \nDépenses d’investissement \n11 000 \n3 564 \n3 511 \n-1,5% \n-1,5% \nDépenses d’intervention \n83 824 \n28 713 \n31 822 \n10,8% \n7,1% \nDépenses d’opérations financières \n1 151 \n683 \n831 \n21,7% \n21,7% \nDépenses du budget général \n314 361 \n111 704 \n116 205 \n4,0% \n3,0% \nPrélèvement sur recettes au profit des collectivités territoriales \n46 461 \n12 980 \n12 076 \n-7,0% \n-6,9% \nPrélèvement sur recettes au profit de l'Union européenne \n18 996 \n6 641 \n6 231 \n-6,2% \n-6,2% \nPrélèvements sur recettes \n65 457 \n19 621 \n18 306 \n-6,7% \n-6,6% \nDépenses (budget général et prélèvements sur recettes) \n379 818 \n131 325 \n134 511 \n2,4% \n1,6% \n \n \nDépenses du budget général (en milliards d’euros) \nvaleurs mensuelles \nécart 2017-2016 (cumul depuis le début de l’année) \n \n10\n15\n20\n25\n30\n35\n40\n45\n50\nJanv.\nFév.\nMars\nAvr.\nMai\nJuin\nJuil.\nAoût\nSept.\nOct.\nNov.\nDéc.\n2016\n2017\n \n-12\n-10\n-8\n-6\n-4\n-2\n0\n2\n4\n6\n8\n10\n12\n14\nJanv.\nFév.\nMars\nAvr.\nMai\nJuin\nJuil.\nAoût\nSept.\nOct.\nNov.\nDéc.\nEcart 2017-2016 à périmètre courant\n \n \n \nLois de finances – exécution (hors FMI)  \n \nen millions d’euros \n2015 \n2016 \n2017 \nLFI \nLFR \nEXE \nLFI \nLFR \nEXE \nLFI \nDépenses  \n371 491 \n372 827 \n371 805 \n380 781 \n381 180 \n379 818 \n385 530 \nPrélèvements sur recettes \n71 471 \n70 434 \n70 230 \n67 474 \n65 497 \n65 457 \n63 064 \nDépenses du budget général (1) (2) \n300 020 \n302 393 \n301 575 \n313 307 \n315 682 \n314 361 \n322 466 \n-   dont dépenses financées hors fonds de concours \n296 096 \n297 569 \n296 462 \n309 736 \n312 111 \n310 729 \n318 536 \n  \n  \n  \n  \n  \n  \n  \n  \nRecettes \n297 250 \n298 320 \n299 656 \n307 080 \n305 405 \n303 967 \n310 783 \nRecettes fiscales nettes (3) \n279 091 \n278 759 \n280 132 \n287 861 \n285 293 \n284 097 \n292 348 \nRecettes non fiscales \n14 234 \n14 736 \n14 412 \n15 648 \n16 542 \n16 238 \n14 505 \nFonds de concours \n3 925 \n4 825 \n5 113 \n3 571 \n3 571 \n3 632 \n3 930 \n  \n  \n  \n  \n  \n  \n  \n  \nSolde des comptes spéciaux (4) \n-187 \n1 167 \n1 624 \n1 387 \n5 813 \n6 795 \n5 412 \nDont avances aux collectivités territoriales \n-216 \n504 \n74 \n827 \n827 \n1 381 \n437 \nSolde général d’exécution (hors budgets annexes) (4) \n-74 428 \n-73 339 \n-70 524 \n-72 314 \n-69 962 \n-69 056 \n-69 335 \nPour mémoire : remboursements et dégrèvements \n99 475 \n101 789 \n103 185 \n100 164 \n104 757 \n103 326 \n108 834 \n \n1) hors remboursements et dégrèvements  (2) le montant des dépenses financées par les fonds de concours est égal, par convention, à celui des recettes encaissées à ce titre \n(3) nettes des remboursements et dégrèvements   (4) hors FMI \n", "published_date": "2017-06-09", "section": "Communiques"}